{"title":"HotAndMean - Alena Croft, Vanessa Cage (Brazzers) ","uid":9843584,"size":227307433,"categoryP":"porn","categoryS":"other","magnet":"?xt=urn:btih:06301c70833bbe583088a312e733d712898afe22&amp;dn=HotAndMean+-+Alena+Croft%2C+Vanessa+Cage+%28Brazzers%29+&amp;tr=udp%3A%2F%2Ftracker.openbittorrent.com%3A80&amp;tr=udp%3A%2F%2Fopen.demonii.com%3A1337&amp;tr=udp%3A%2F%2Ftracker.coppersurfer.tk%3A6969&amp;tr=udp%3A%2F%2Fexodus.desync.com%3A6969","seeders":0,"leechers":1,"uploader":"codho","files":1,"time":1396033426,"description":"Alena Croft is a sexy stripper, shaking her stuff for all the horny dudes who come in to see her little peep show. Her coworker Vanessa is annoyed that Alena keeps taking her hours and her clients, so she decides to teach her a little lesson. While Alena is busy dancing for a customer, Vanessa comes in with a blindfold and a strap-on to really give the guy a show! Alena sucks and titty fucks that plastic dick before banding over and spreading her luscious legs to get fucked by her lesbian lover! They use vibes, their strap-on, and even their tongues to get each other off, and as they both reach climax, the guy on the other side of the glass can barely believe his luck!\n\n\nScreenshot :\n &lt;a href=&quot;\nhttp://imgdope.com/viewer.php?file=54088501824192558575.jpg&quot; rel=&quot;nofollow&quot; target=&quot;_NEW&quot;&gt;\nhttp://imgdope.com/viewer.php?file=54088501824192558575.jpg&lt;/a&gt;\n &lt;a href=&quot;\nhttp://imgdope.com/viewer.php?file=65544711635870100438.jpg&quot; rel=&quot;nofollow&quot; target=&quot;_NEW&quot;&gt;\nhttp://imgdope.com/viewer.php?file=65544711635870100438.jpg&lt;/a&gt;","torrent":{"xt":"urn:btih:06301c70833bbe583088a312e733d712898afe22","amp;dn":"HotAndMean+-+Alena+Croft%2C+Vanessa+Cage+%28Brazzers%29+","amp;tr":["udp%3A%2F%2Ftracker.openbittorrent.com%3A80","udp%3A%2F%2Fopen.demonii.com%3A1337","udp%3A%2F%2Ftracker.coppersurfer.tk%3A6969","udp%3A%2F%2Fexodus.desync.com%3A6969"],"infoHash":"06301c70833bbe583088a312e733d712898afe22","infoHashBuffer":{"type":"Buffer","data":[6,48,28,112,131,59,190,88,48,136,163,18,231,51,215,18,137,138,254,34]},"announce":[],"urlList":[]}}