{"title":"GloryHoleLoads - Sindy Lange [Sindy Lange Sucks 2 Cocks and Fuck","uid":9794958,"size":151618658,"categoryP":"porn","categoryS":"other","magnet":"?xt=urn:btih:08b5b6fc44fa96fafa763b6ba6bf83cd95e0b0f1&amp;dn=GloryHoleLoads+-+Sindy+Lange+%5BSindy+Lange+Sucks+2+Cocks+and+Fuck&amp;tr=udp%3A%2F%2Ftracker.openbittorrent.com%3A80&amp;tr=udp%3A%2F%2Fopen.demonii.com%3A1337&amp;tr=udp%3A%2F%2Ftracker.coppersurfer.tk%3A6969&amp;tr=udp%3A%2F%2Fexodus.desync.com%3A6969","seeders":0,"leechers":1,"uploader":"codho","files":1,"time":1395300026,"description":"Screenshot :\n &lt;a href=&quot;\nhttp://imgdope.com/viewer.php?file=14835843177130873080.jpg&quot; rel=&quot;nofollow&quot; target=&quot;_NEW&quot;&gt;\nhttp://imgdope.com/viewer.php?file=14835843177130873080.jpg&lt;/a&gt;\n &lt;a href=&quot;\nhttp://imgdope.com/viewer.php?file=35487058128505186863.jpg&quot; rel=&quot;nofollow&quot; target=&quot;_NEW&quot;&gt;\nhttp://imgdope.com/viewer.php?file=35487058128505186863.jpg&lt;/a&gt;","torrent":{"xt":"urn:btih:08b5b6fc44fa96fafa763b6ba6bf83cd95e0b0f1","amp;dn":"GloryHoleLoads+-+Sindy+Lange+%5BSindy+Lange+Sucks+2+Cocks+and+Fuck","amp;tr":["udp%3A%2F%2Ftracker.openbittorrent.com%3A80","udp%3A%2F%2Fopen.demonii.com%3A1337","udp%3A%2F%2Ftracker.coppersurfer.tk%3A6969","udp%3A%2F%2Fexodus.desync.com%3A6969"],"infoHash":"08b5b6fc44fa96fafa763b6ba6bf83cd95e0b0f1","infoHashBuffer":{"type":"Buffer","data":[8,181,182,252,68,250,150,250,250,118,59,107,166,191,131,205,149,224,176,241]},"announce":[],"urlList":[]}}