{"title":"[RealWifeStories] Vanilla Deville, Jessa Rhodes (Happy Get On Yo","uid":8421861,"size":3666336542,"categoryP":"porn","categoryS":"hd___movies","magnet":"?xt=urn:btih:13c3590f5c4c50aa497aa641eb4d6393e4c2ae3d&amp;dn=%5BRealWifeStories%5D+Vanilla+Deville%2C+Jessa+Rhodes+%28Happy+Get+On+Yo&amp;tr=udp%3A%2F%2Ftracker.openbittorrent.com%3A80&amp;tr=udp%3A%2F%2Fopen.demonii.com%3A1337&amp;tr=udp%3A%2F%2Ftracker.coppersurfer.tk%3A6969&amp;tr=udp%3A%2F%2Fexodus.desync.com%3A6969","seeders":0,"leechers":3,"uploader":"chkm8te","files":1,"time":1367217897,"description":"[RealWifeStories] Vanilla Deville, Jessa Rhodes (Happy Get On Your Knees Day / 04.29.2013)\nres:1080p\n\nIt's Johnny's birthday, and His wife is Vanilla Throwing HIM A Surprise with colleagues and All His Friends. But Jessa from the office is bored as hell, and the only fuckable guy at the party is Johnny! Good thing Vanilla is willing to grant her husband one incredible birthday wish. As much as the ladies hate each other, they're happy to put their feelings aside for a good old fashioned fuckfest. \n\nScreens: &lt;a href=&quot;\nhttp://xxxhost.me/viewer.php?file=epkasdmhl6nl5zofx3jn.jpg&quot; rel=&quot;nofollow&quot; target=&quot;_NEW&quot;&gt;\nhttp://xxxhost.me/viewer.php?file=epkasdmhl6nl5zofx3jn.jpg&lt;/a&gt;\n &lt;a href=&quot;\nhttp://xxxhost.me/viewer.php?file=deujsaqa2nenbf47neip.jpg&quot; rel=&quot;nofollow&quot; target=&quot;_NEW&quot;&gt;\nhttp://xxxhost.me/viewer.php?file=deujsaqa2nenbf47neip.jpg&lt;/a&gt;","torrent":{"xt":"urn:btih:13c3590f5c4c50aa497aa641eb4d6393e4c2ae3d","amp;dn":"%5BRealWifeStories%5D+Vanilla+Deville%2C+Jessa+Rhodes+%28Happy+Get+On+Yo","amp;tr":["udp%3A%2F%2Ftracker.openbittorrent.com%3A80","udp%3A%2F%2Fopen.demonii.com%3A1337","udp%3A%2F%2Ftracker.coppersurfer.tk%3A6969","udp%3A%2F%2Fexodus.desync.com%3A6969"],"infoHash":"13c3590f5c4c50aa497aa641eb4d6393e4c2ae3d","infoHashBuffer":{"type":"Buffer","data":[19,195,89,15,92,76,80,170,73,122,166,65,235,77,99,147,228,194,174,61]},"announce":[],"urlList":[]}}