{"title":"MET-ART One Hit Wonders V part 5","uid":9684732,"size":2174439281,"categoryP":"porn","categoryS":"pictures","magnet":"?xt=urn:btih:19d9b2e1c2ac4bca6a6a35dc16ec9a5cc96663b7&amp;dn=MET-ART+One+Hit+Wonders+V+part+5&amp;tr=udp%3A%2F%2Ftracker.openbittorrent.com%3A80&amp;tr=udp%3A%2F%2Fopen.demonii.com%3A1337&amp;tr=udp%3A%2F%2Ftracker.coppersurfer.tk%3A6969&amp;tr=udp%3A%2F%2Fexodus.desync.com%3A6969","seeders":0,"leechers":5,"uploader":"yourothermom","files":1283,"time":1393741162,"description":"MET-ART one hit wonders\n\nModels with only one set.\n\nLetter V\n\nW X Y and Z coming up next...\n\nAll letter V covers here: &lt;a href=&quot; http://bayimg.com/album/paaImAaac&quot; rel=&quot;nofollow&quot; target=&quot;_NEW&quot;&gt; http://bayimg.com/album/paaImAaac&lt;/a&gt;\n\nViki F &lt;a href=&quot;\nhttp://bayimg.com/baKfgAafh&quot; rel=&quot;nofollow&quot; target=&quot;_NEW&quot;&gt;\nhttp://bayimg.com/baKfgAafh&lt;/a&gt;\n\n\nViki G &lt;a href=&quot;\nhttp://bayimg.com/bAkfHAAfh&quot; rel=&quot;nofollow&quot; target=&quot;_NEW&quot;&gt;\nhttp://bayimg.com/bAkfHAAfh&lt;/a&gt;\n\n\nVikka A &lt;a href=&quot;\nhttp://bayimg.com/BakFIAaFh&quot; rel=&quot;nofollow&quot; target=&quot;_NEW&quot;&gt;\nhttp://bayimg.com/BakFIAaFh&lt;/a&gt;\n\n\nViktoria B &lt;a href=&quot;\nhttp://bayimg.com/BAKfjAaFh&quot; rel=&quot;nofollow&quot; target=&quot;_NEW&quot;&gt;\nhttp://bayimg.com/BAKfjAaFh&lt;/a&gt;\n\n\nViktoriya A &lt;a href=&quot;\nhttp://bayimg.com/bakfkAAfh&quot; rel=&quot;nofollow&quot; target=&quot;_NEW&quot;&gt;\nhttp://bayimg.com/bakfkAAfh&lt;/a&gt;\n\n\nViky Muna &lt;a href=&quot;\nhttp://bayimg.com/BakFlAaFH&quot; rel=&quot;nofollow&quot; target=&quot;_NEW&quot;&gt;\nhttp://bayimg.com/BakFlAaFH&lt;/a&gt;\n\n\nViola C &lt;a href=&quot;\nhttp://bayimg.com/bAkfMaafH&quot; rel=&quot;nofollow&quot; target=&quot;_NEW&quot;&gt;\nhttp://bayimg.com/bAkfMaafH&lt;/a&gt;\n\n\nVita B &lt;a href=&quot;\nhttp://bayimg.com/BAKFnAafh&quot; rel=&quot;nofollow&quot; target=&quot;_NEW&quot;&gt;\nhttp://bayimg.com/BAKFnAafh&lt;/a&gt;\n\n\nViviana A &lt;a href=&quot;\nhttp://bayimg.com/bAKfOAAfH&quot; rel=&quot;nofollow&quot; target=&quot;_NEW&quot;&gt;\nhttp://bayimg.com/bAKfOAAfH&lt;/a&gt;\n\n\nVivienne A &lt;a href=&quot;\nhttp://bayimg.com/BakfpaAFH&quot; rel=&quot;nofollow&quot; target=&quot;_NEW&quot;&gt;\nhttp://bayimg.com/BakfpaAFH&lt;/a&gt;\n\n","torrent":{"xt":"urn:btih:19d9b2e1c2ac4bca6a6a35dc16ec9a5cc96663b7","amp;dn":"MET-ART+One+Hit+Wonders+V+part+5","amp;tr":["udp%3A%2F%2Ftracker.openbittorrent.com%3A80","udp%3A%2F%2Fopen.demonii.com%3A1337","udp%3A%2F%2Ftracker.coppersurfer.tk%3A6969","udp%3A%2F%2Fexodus.desync.com%3A6969"],"infoHash":"19d9b2e1c2ac4bca6a6a35dc16ec9a5cc96663b7","infoHashBuffer":{"type":"Buffer","data":[25,217,178,225,194,172,75,202,106,106,53,220,22,236,154,92,201,102,99,183]},"announce":[],"urlList":[]}}