{"title":"DVJ BAZUKA - Play My Music Loud.mp4","uid":9660823,"size":46554960,"categoryP":"porn","categoryS":"other","magnet":"?xt=urn:btih:29622f524efc12b15125997772a404ecc441f8dd&amp;dn=DVJ+BAZUKA+-+Play+My+Music+Loud.mp4&amp;tr=udp%3A%2F%2Ftracker.openbittorrent.com%3A80&amp;tr=udp%3A%2F%2Fopen.demonii.com%3A1337&amp;tr=udp%3A%2F%2Ftracker.coppersurfer.tk%3A6969&amp;tr=udp%3A%2F%2Fexodus.desync.com%3A6969","seeders":0,"leechers":0,"uploader":null,"files":-1,"time":1393276199,"description":"DVJ BAZUKA - Play My Music Loud. HD 720\nErotic video clip","torrent":{"xt":"urn:btih:29622f524efc12b15125997772a404ecc441f8dd","amp;dn":"DVJ+BAZUKA+-+Play+My+Music+Loud.mp4","amp;tr":["udp%3A%2F%2Ftracker.openbittorrent.com%3A80","udp%3A%2F%2Fopen.demonii.com%3A1337","udp%3A%2F%2Ftracker.coppersurfer.tk%3A6969","udp%3A%2F%2Fexodus.desync.com%3A6969"],"infoHash":"29622f524efc12b15125997772a404ecc441f8dd","infoHashBuffer":{"type":"Buffer","data":[41,98,47,82,78,252,18,177,81,37,153,119,114,164,4,236,196,65,248,221]},"announce":[],"urlList":[]}}