{"title":"Bikini.Bang.Bang.XXX.BDRiP.x264-PORNOLATiON","uid":9789389,"size":1134950446,"categoryP":"porn","categoryS":"movies","magnet":"?xt=urn:btih:30cb23f03abd19a8add924b92db56e27b5a90fac&amp;dn=Bikini.Bang.Bang.XXX.BDRiP.x264-PORNOLATiON&amp;tr=udp%3A%2F%2Ftracker.openbittorrent.com%3A80&amp;tr=udp%3A%2F%2Fopen.demonii.com%3A1337&amp;tr=udp%3A%2F%2Ftracker.coppersurfer.tk%3A6969&amp;tr=udp%3A%2F%2Fexodus.desync.com%3A6969","seeders":0,"leechers":1,"uploader":"xxxlavalxxx","files":4,"time":1395224412,"description":"Feature porn for couples! Everyday is a party for these four sexy surfer gals in, who live their lives to the fullest--hitting the waves, partying and screwing random men! In one violent moment, their erotic paradise is forever destroyed. After a night of steamy, hardcore sex, Chloe Foster wakes up to witness her boyfriend dragged to the next room and shot by a ruthless thug!\nPanicked, Chloe tries to escape but is caught in the process. In order to save their friend, beach babes Rilynn Rae and Sierra Day and Kiera Winters most toss aside their surf boards and dive head first into a dark, new world. Luckily they find the perfect guide in Tommy Gunn, a mysterious stranger who tempts them into illicit missions, as addictive as they are dangerous!\n\nChloe Foster, Kiera Winters, Rilynn Rae, Romi Rain, Sierra Day\n\n &lt;a href=&quot;\nhttp://imgdone.com/viewer.php?file=39361101783721254849.jpeg&quot; rel=&quot;nofollow&quot; target=&quot;_NEW&quot;&gt;\nhttp://imgdone.com/viewer.php?file=39361101783721254849.jpeg&lt;/a&gt;\n &lt;a href=&quot;\nhttp://imgdone.com/viewer.php?file=60121620924417870176.jpeg&quot; rel=&quot;nofollow&quot; target=&quot;_NEW&quot;&gt;\nhttp://imgdone.com/viewer.php?file=60121620924417870176.jpeg&lt;/a&gt;","torrent":{"xt":"urn:btih:30cb23f03abd19a8add924b92db56e27b5a90fac","amp;dn":"Bikini.Bang.Bang.XXX.BDRiP.x264-PORNOLATiON","amp;tr":["udp%3A%2F%2Ftracker.openbittorrent.com%3A80","udp%3A%2F%2Fopen.demonii.com%3A1337","udp%3A%2F%2Ftracker.coppersurfer.tk%3A6969","udp%3A%2F%2Fexodus.desync.com%3A6969"],"infoHash":"30cb23f03abd19a8add924b92db56e27b5a90fac","infoHashBuffer":{"type":"Buffer","data":[48,203,35,240,58,189,25,168,173,217,36,185,45,181,110,39,181,169,15,172]},"announce":[],"urlList":[]}}