{"title":"AssParade - Sexy Petite PornStar - Jynx Maze.mp4","uid":9779404,"size":385360619,"categoryP":"porn","categoryS":"movie_clips","magnet":"?xt=urn:btih:35c8d0e8b660e3ae4965921ba4d415d7614e0458&amp;dn=AssParade+-+Sexy+Petite+PornStar+-+Jynx+Maze.mp4&amp;tr=udp%3A%2F%2Ftracker.openbittorrent.com%3A80&amp;tr=udp%3A%2F%2Fopen.demonii.com%3A1337&amp;tr=udp%3A%2F%2Ftracker.coppersurfer.tk%3A6969&amp;tr=udp%3A%2F%2Fexodus.desync.com%3A6969","seeders":0,"leechers":1,"uploader":"Pornmaze","files":-1,"time":1395081758,"description":"AssParade - Sexy Petite PornStar - Jynx Maze.mp4\n\n2014, Natural Tits, Blowjob, Brunette, Cumshot, Facial, Handjob, Swallow, Hardcore, XXX, Adult\n\n720 x 404\n\n00:46:45\n\n367.51 MB\n\nScreens\n &lt;a href=&quot;\nhttp://www.pixsor.com/share-D75E_5327325E.html&quot; rel=&quot;nofollow&quot; target=&quot;_NEW&quot;&gt;\nhttp://www.pixsor.com/share-D75E_5327325E.html&lt;/a&gt;\n &lt;a href=&quot;\nhttp://www.pixsor.com/share-3DDD_5327325F.html&quot; rel=&quot;nofollow&quot; target=&quot;_NEW&quot;&gt;\nhttp://www.pixsor.com/share-3DDD_5327325F.html&lt;/a&gt;","torrent":{"xt":"urn:btih:35c8d0e8b660e3ae4965921ba4d415d7614e0458","amp;dn":"AssParade+-+Sexy+Petite+PornStar+-+Jynx+Maze.mp4","amp;tr":["udp%3A%2F%2Ftracker.openbittorrent.com%3A80","udp%3A%2F%2Fopen.demonii.com%3A1337","udp%3A%2F%2Ftracker.coppersurfer.tk%3A6969","udp%3A%2F%2Fexodus.desync.com%3A6969"],"infoHash":"35c8d0e8b660e3ae4965921ba4d415d7614e0458","infoHashBuffer":{"type":"Buffer","data":[53,200,208,232,182,96,227,174,73,101,146,27,164,212,21,215,97,78,4,88]},"announce":[],"urlList":[]}}