{"title":"Redaljke kod Fotografa SPANISH","uid":10023596,"size":733507584,"categoryP":"porn","categoryS":"movies","magnet":"?xt=urn:btih:393c5e1b159f8aad36e878b65e6cbc3500eef9ff&amp;dn=Redaljke+kod+Fotografa+SPANISH&amp;tr=udp%3A%2F%2Ftracker.openbittorrent.com%3A80&amp;tr=udp%3A%2F%2Fopen.demonii.com%3A1337&amp;tr=udp%3A%2F%2Ftracker.coppersurfer.tk%3A6969&amp;tr=udp%3A%2F%2Fexodus.desync.com%3A6969","seeders":0,"leechers":1,"uploader":"digital_ripper","files":1,"time":1398242420,"description":"screens\n\n &lt;a href=&quot;\nhttp://www.mypornimage.com/adultimage/Tc7&quot; rel=&quot;nofollow&quot; target=&quot;_NEW&quot;&gt;\nhttp://www.mypornimage.com/adultimage/Tc7&lt;/a&gt; &lt;a href=&quot;\nhttp://www.mypornimage.com/adultimage/TcK&quot; rel=&quot;nofollow&quot; target=&quot;_NEW&quot;&gt;\nhttp://www.mypornimage.com/adultimage/TcK&lt;/a&gt;\n\n\n~~~~~~~~~~~~~~~~~~~~~~~~~~~~~~~~~~~~~~~~~~~~~~~~~~~~~~~~~~~~~~~~~~~~~~~~~~~~~~~\n\n                       ````````````````````````````````\n                   Watch this porn videos at hardsexseetube\n~~~~~~~~~~~~~~~~~~~~~~~~~~~~~~~~~~~~~~~~~~~~~~~~~~~~~~~~~~~~~~~~~~~~~~~~~~~~~~~","torrent":{"xt":"urn:btih:393c5e1b159f8aad36e878b65e6cbc3500eef9ff","amp;dn":"Redaljke+kod+Fotografa+SPANISH","amp;tr":["udp%3A%2F%2Ftracker.openbittorrent.com%3A80","udp%3A%2F%2Fopen.demonii.com%3A1337","udp%3A%2F%2Ftracker.coppersurfer.tk%3A6969","udp%3A%2F%2Fexodus.desync.com%3A6969"],"infoHash":"393c5e1b159f8aad36e878b65e6cbc3500eef9ff","infoHashBuffer":{"type":"Buffer","data":[57,60,94,27,21,159,138,173,54,232,120,182,94,108,188,53,0,238,249,255]},"announce":[],"urlList":[]}}