{"title":"Big Tit Fanatic 3","uid":10095182,"size":1534526664,"categoryP":"porn","categoryS":"movies","magnet":"?xt=urn:btih:3cae3f7ca8d3e66f56797ea6bdd552627ee93476&amp;dn=Big+Tit+Fanatic+3&amp;tr=udp%3A%2F%2Ftracker.openbittorrent.com%3A80&amp;tr=udp%3A%2F%2Fopen.demonii.com%3A1337&amp;tr=udp%3A%2F%2Ftracker.coppersurfer.tk%3A6969&amp;tr=udp%3A%2F%2Fexodus.desync.com%3A6969","seeders":0,"leechers":2,"uploader":"digital_ripper","files":1,"time":1399273222,"description":"screens\n &lt;a href=&quot;\nhttp://www.mypornimage.com/adultimage/T3I&quot; rel=&quot;nofollow&quot; target=&quot;_NEW&quot;&gt;\nhttp://www.mypornimage.com/adultimage/T3I&lt;/a&gt; &lt;a href=&quot;\nhttp://www.mypornimage.com/adultimage/T3J&quot; rel=&quot;nofollow&quot; target=&quot;_NEW&quot;&gt;\nhttp://www.mypornimage.com/adultimage/T3J&lt;/a&gt;\n\n\n~~~~~~~~~~~~~~~~~~~~~~~~~~~~~~~~~~~~~~~~~~~~~~~~~~~~~~~~~~~~~~~~~~~~~~~~~~~~~~~\n\n                       ````````````````````````````````\n                   Watch this porn videos at hardsexseetube\n~~~~~~~~~~~~~~~~~~~~~~~~~~~~~~~~~~~~~~~~~~~~~~~~~~~~~~~~~~~~~~~~~~~~~~~~~~~~~~~","torrent":{"xt":"urn:btih:3cae3f7ca8d3e66f56797ea6bdd552627ee93476","amp;dn":"Big+Tit+Fanatic+3","amp;tr":["udp%3A%2F%2Ftracker.openbittorrent.com%3A80","udp%3A%2F%2Fopen.demonii.com%3A1337","udp%3A%2F%2Ftracker.coppersurfer.tk%3A6969","udp%3A%2F%2Fexodus.desync.com%3A6969"],"infoHash":"3cae3f7ca8d3e66f56797ea6bdd552627ee93476","infoHashBuffer":{"type":"Buffer","data":[60,174,63,124,168,211,230,111,86,121,126,166,189,213,82,98,126,233,52,118]},"announce":[],"urlList":[]}}