{"title":"NubileFilms - Pound It - Krissie [1080p].mp4","uid":9715262,"size":586188018,"categoryP":"porn","categoryS":"hd___movies","magnet":"?xt=urn:btih:3dd3fe5c804105d08a95c5f2e58964ce7df480c2&amp;dn=NubileFilms+-+Pound+It+-+Krissie+%5B1080p%5D.mp4&amp;tr=udp%3A%2F%2Ftracker.openbittorrent.com%3A80&amp;tr=udp%3A%2F%2Fopen.demonii.com%3A1337&amp;tr=udp%3A%2F%2Ftracker.coppersurfer.tk%3A6969&amp;tr=udp%3A%2F%2Fexodus.desync.com%3A6969","seeders":0,"leechers":1,"uploader":"C3Porno","files":-1,"time":1394150347,"description":"NubileFilms - Pound It - Krissie [1080p].mp4\n\n2014, All Sex, Straight, Oral, Hardcore, Cuckold, HD, XXX, Adult\n\n1920 x 1080\n\n00:12:30\n\n559.03 MB \n\nScreens\n &lt;a href=&quot;\nhttp://www.euro-pic.eu/share-F6D6_5318FBCC.html&quot; rel=&quot;nofollow&quot; target=&quot;_NEW&quot;&gt;\nhttp://www.euro-pic.eu/share-F6D6_5318FBCC.html&lt;/a&gt;\n &lt;a href=&quot;\nhttp://www.euro-pic.eu/share-E0F6_5318FBCC.html&quot; rel=&quot;nofollow&quot; target=&quot;_NEW&quot;&gt;\nhttp://www.euro-pic.eu/share-E0F6_5318FBCC.html&lt;/a&gt;\n &lt;a href=&quot;\nhttp://www.euro-pic.eu/share-3348_5318FBCC.html&quot; rel=&quot;nofollow&quot; target=&quot;_NEW&quot;&gt;\nhttp://www.euro-pic.eu/share-3348_5318FBCC.html&lt;/a&gt;\n &lt;a href=&quot;\nhttp://www.euro-pic.eu/share-27F8_5318FBCC.html&quot; rel=&quot;nofollow&quot; target=&quot;_NEW&quot;&gt;\nhttp://www.euro-pic.eu/share-27F8_5318FBCC.html&lt;/a&gt;\n &lt;a href=&quot;\nhttp://www.euro-pic.eu/share-77C9_5318FBCC.html&quot; rel=&quot;nofollow&quot; target=&quot;_NEW&quot;&gt;\nhttp://www.euro-pic.eu/share-77C9_5318FBCC.html&lt;/a&gt;","torrent":{"xt":"urn:btih:3dd3fe5c804105d08a95c5f2e58964ce7df480c2","amp;dn":"NubileFilms+-+Pound+It+-+Krissie+%5B1080p%5D.mp4","amp;tr":["udp%3A%2F%2Ftracker.openbittorrent.com%3A80","udp%3A%2F%2Fopen.demonii.com%3A1337","udp%3A%2F%2Ftracker.coppersurfer.tk%3A6969","udp%3A%2F%2Fexodus.desync.com%3A6969"],"infoHash":"3dd3fe5c804105d08a95c5f2e58964ce7df480c2","infoHashBuffer":{"type":"Buffer","data":[61,211,254,92,128,65,5,208,138,149,197,242,229,137,100,206,125,244,128,194]},"announce":[],"urlList":[]}}