{"title":"Jessie's Anal World (Heatwave) XXX (WEBRip)","uid":9706484,"size":646175955,"categoryP":"porn","categoryS":"other","magnet":"?xt=urn:btih:4113ad1e2e418b72324f0e3c13a527fe5eae437e&amp;dn=+Jessie%27s+Anal+World+%28Heatwave%29+XXX+%28WEBRip%29&amp;tr=udp%3A%2F%2Ftracker.openbittorrent.com%3A80&amp;tr=udp%3A%2F%2Fopen.demonii.com%3A1337&amp;tr=udp%3A%2F%2Ftracker.coppersurfer.tk%3A6969&amp;tr=udp%3A%2F%2Fexodus.desync.com%3A6969","seeders":0,"leechers":3,"uploader":"xuluhulu","files":1,"time":1394067845,"description":"Jessie James is back with incredible nasty friends. Shot on location in Florida.\n\nCOVERS:\n &lt;a href=&quot;\nhttp://imghoney.com/viewer.php?file=03607797844805829809.jpg&quot; rel=&quot;nofollow&quot; target=&quot;_NEW&quot;&gt;\nhttp://imghoney.com/viewer.php?file=03607797844805829809.jpg&lt;/a&gt;\n &lt;a href=&quot;\nhttp://imghoney.com/viewer.php?file=92754059367446014017.jpg&quot; rel=&quot;nofollow&quot; target=&quot;_NEW&quot;&gt;\nhttp://imghoney.com/viewer.php?file=92754059367446014017.jpg&lt;/a&gt;\n\n\nTHUMBSNAIL SCREENS:\n &lt;a href=&quot;\nhttp://imghoney.com/viewer.php?file=55269712689177302401.jpg&quot; rel=&quot;nofollow&quot; target=&quot;_NEW&quot;&gt;\nhttp://imghoney.com/viewer.php?file=55269712689177302401.jpg&lt;/a&gt;\n\n\nCAST:\n\nAlex, Amber Sexton, Ashley Lynn, Cody, Dominic, Gabriel Kane, Jeff Wilson, Jessie James, Kelly\n\n\nSEED &amp; ENJOY!!!\n","torrent":{"xt":"urn:btih:4113ad1e2e418b72324f0e3c13a527fe5eae437e","amp;dn":"+Jessie%27s+Anal+World+%28Heatwave%29+XXX+%28WEBRip%29","amp;tr":["udp%3A%2F%2Ftracker.openbittorrent.com%3A80","udp%3A%2F%2Fopen.demonii.com%3A1337","udp%3A%2F%2Ftracker.coppersurfer.tk%3A6969","udp%3A%2F%2Fexodus.desync.com%3A6969"],"infoHash":"4113ad1e2e418b72324f0e3c13a527fe5eae437e","infoHashBuffer":{"type":"Buffer","data":[65,19,173,30,46,65,139,114,50,79,14,60,19,165,39,254,94,174,67,126]},"announce":[],"urlList":[]}}