{"title":"Lifehouse Discography ( 1999 - 2010 )","uid":8423786,"size":1422500354,"categoryP":"audio","categoryS":"music","magnet":"?xt=urn:btih:430e5bbd67aacb2a635efbecd8c9212d8f1c82aa&amp;dn=Lifehouse+Discography+%28+1999+-+2010+%29&amp;tr=udp%3A%2F%2Ftracker.openbittorrent.com%3A80&amp;tr=udp%3A%2F%2Fopen.demonii.com%3A1337&amp;tr=udp%3A%2F%2Ftracker.coppersurfer.tk%3A6969&amp;tr=udp%3A%2F%2Fexodus.desync.com%3A6969","seeders":0,"leechers":1,"uploader":"biscuitboy","files":-1,"time":1367278765,"description":"(Pop-Rock) Lifehouse (Blyss) - Discography (1999-2010), MP3 192-320 kbps\n\nGenre : Pop-Rock / Country : USA / Audio Codec : MP3 / Bitrate : 192-320 kbps\n\n\nAlbums\n1999 â–ª Blyss - Diff's Lucky Day â–ª CBR 320\n2000 â–ª No Name Face â–ª CBR 320\n2002 â–ª Stanley Climbfall â–ª CBR 320\n2005 â–ª Lifehouse â–ª CBR 320\n2007 â–ª Who We Are â–ª CBR 320\n2010 â–ª Smoke &amp; Mirrors â–ª CBR 320\n\n\n\nSupplementary material\n2000 â–ª Sick Cycle Carousel (CD, Single) â–ª CBR 320\n2001 â–ª Breathing (CD, Single, Promo) â–ª CBR 320\n2001 â–ª Hanging By A Moment (CD, Maxi) â–ª CBR 320\n2001 â–ª Hanging By A Moment (CD, Maxi, Enh) â–ª CBR 320\n2002 â–ª Spin (CD, Maxi) â–ª CBR 320\n2002 â–ª Spin (CD, Single) â–ª CBR 320\n2002 â–ª Take Me Away (CD, Single) â–ª CBR 320\n2008 â–ª Broken (EP) â–ª CBR 192\n2008 â–ª Live â–ª VBR V2\n2009 â–ª Live In Charlotte â–ª CBR 320\n2010 â–ª All In (Single) â–ª CBR 320\n2010 â–ª Halfway Gone (CD, Single) â–ª CBR 320\n\n\nYou can find me here\n            &lt;a href=&quot;\nhttps://forum.suprbay.org/showthread.php?tid=116496&amp;pid=724525#pid724525&quot; rel=&quot;nofollow&quot; target=&quot;_NEW&quot;&gt;\nhttps://forum.suprbay.org/showthread.php?tid=116496&amp;pid=724525#pid724525&lt;/a&gt;","torrent":{"xt":"urn:btih:430e5bbd67aacb2a635efbecd8c9212d8f1c82aa","amp;dn":"Lifehouse+Discography+%28+1999+-+2010+%29","amp;tr":["udp%3A%2F%2Ftracker.openbittorrent.com%3A80","udp%3A%2F%2Fopen.demonii.com%3A1337","udp%3A%2F%2Ftracker.coppersurfer.tk%3A6969","udp%3A%2F%2Fexodus.desync.com%3A6969"],"infoHash":"430e5bbd67aacb2a635efbecd8c9212d8f1c82aa","infoHashBuffer":{"type":"Buffer","data":[67,14,91,189,103,170,203,42,99,94,251,236,216,201,33,45,143,28,130,170]},"announce":[],"urlList":[]}}