{"title":"[ShadyPI] Carmen Callaway (Sexual Slut Surprise / 05.20.2013)","uid":8495313,"size":450469041,"categoryP":"porn","categoryS":"movies","magnet":"?xt=urn:btih:4b4a6bf4b4295e93520d0ccd8b63e9c555ab2ca3&amp;dn=%5BShadyPI%5D+Carmen+Callaway+%28Sexual+Slut+Surprise+%2F+05.20.2013%29&amp;tr=udp%3A%2F%2Ftracker.openbittorrent.com%3A80&amp;tr=udp%3A%2F%2Fopen.demonii.com%3A1337&amp;tr=udp%3A%2F%2Ftracker.coppersurfer.tk%3A6969&amp;tr=udp%3A%2F%2Fexodus.desync.com%3A6969","seeders":0,"leechers":0,"uploader":"chkm8te","files":1,"time":1369125970,"description":"[ShadyPI] Carmen Callaway (Sexual Slut Surprise / 05.20.2013)\n\nCarmen is one Horny Slut! \nShe wanted to Surprise her Lover by sneaking away from her husband and Opening up her twat for thick A Cheating Dick Inside of her!\n\nScreens: &lt;a href=&quot;\nhttp://xxxhost.me/viewer.php?file=xqe6o0xlw565ijyy0wc5.jpg&quot; rel=&quot;nofollow&quot; target=&quot;_NEW&quot;&gt;\nhttp://xxxhost.me/viewer.php?file=xqe6o0xlw565ijyy0wc5.jpg&lt;/a&gt;\n &lt;a href=&quot;\nhttp://xxxhost.me/viewer.php?file=cbw8uys2s3iye430hwvm.jpg&quot; rel=&quot;nofollow&quot; target=&quot;_NEW&quot;&gt;\nhttp://xxxhost.me/viewer.php?file=cbw8uys2s3iye430hwvm.jpg&lt;/a&gt;","torrent":{"xt":"urn:btih:4b4a6bf4b4295e93520d0ccd8b63e9c555ab2ca3","amp;dn":"%5BShadyPI%5D+Carmen+Callaway+%28Sexual+Slut+Surprise+%2F+05.20.2013%29","amp;tr":["udp%3A%2F%2Ftracker.openbittorrent.com%3A80","udp%3A%2F%2Fopen.demonii.com%3A1337","udp%3A%2F%2Ftracker.coppersurfer.tk%3A6969","udp%3A%2F%2Fexodus.desync.com%3A6969"],"infoHash":"4b4a6bf4b4295e93520d0ccd8b63e9c555ab2ca3","infoHashBuffer":{"type":"Buffer","data":[75,74,107,244,180,41,94,147,82,13,12,205,139,99,233,197,85,171,44,163]},"announce":[],"urlList":[]}}