{"title":"Korporate Kougars.DVDRip.XxX.avi","uid":9703813,"size":728590336,"categoryP":"porn","categoryS":"movies","magnet":"?xt=urn:btih:4be337215ebbeb6a922cacf819719c6f1c50f068&amp;dn=Korporate+Kougars.DVDRip.XxX.avi&amp;tr=udp%3A%2F%2Ftracker.openbittorrent.com%3A80&amp;tr=udp%3A%2F%2Fopen.demonii.com%3A1337&amp;tr=udp%3A%2F%2Ftracker.coppersurfer.tk%3A6969&amp;tr=udp%3A%2F%2Fexodus.desync.com%3A6969","seeders":0,"leechers":0,"uploader":"handsome_hulk1253","files":1,"time":1394040498,"description":"Screenshots\n &lt;a href=&quot;\nhttp://adultxpictures.com/xxx/9gX&quot; rel=&quot;nofollow&quot; target=&quot;_NEW&quot;&gt;\nhttp://adultxpictures.com/xxx/9gX&lt;/a&gt; &lt;a href=&quot;\nhttp://adultxpictures.com/xxx/9gs&quot; rel=&quot;nofollow&quot; target=&quot;_NEW&quot;&gt;\nhttp://adultxpictures.com/xxx/9gs&lt;/a&gt;","torrent":{"xt":"urn:btih:4be337215ebbeb6a922cacf819719c6f1c50f068","amp;dn":"Korporate+Kougars.DVDRip.XxX.avi","amp;tr":["udp%3A%2F%2Ftracker.openbittorrent.com%3A80","udp%3A%2F%2Fopen.demonii.com%3A1337","udp%3A%2F%2Ftracker.coppersurfer.tk%3A6969","udp%3A%2F%2Fexodus.desync.com%3A6969"],"infoHash":"4be337215ebbeb6a922cacf819719c6f1c50f068","infoHashBuffer":{"type":"Buffer","data":[75,227,55,33,94,187,235,106,146,44,172,248,25,113,156,111,28,80,240,104]},"announce":[],"urlList":[]}}