{"title":"UltimateSurrender--US-35363 Jayogen, Izamar Gutierrez, Sasha Pri","uid":9969385,"size":3118853359,"categoryP":"porn","categoryS":"hd___movies","magnet":"?xt=urn:btih:55c32c3a99e86ff37b9346de033e4277ec1766fe&amp;dn=UltimateSurrender--US-35363+Jayogen%2C+Izamar+Gutierrez%2C+Sasha+Pri&amp;tr=udp%3A%2F%2Ftracker.openbittorrent.com%3A80&amp;tr=udp%3A%2F%2Fopen.demonii.com%3A1337&amp;tr=udp%3A%2F%2Ftracker.coppersurfer.tk%3A6969&amp;tr=udp%3A%2F%2Fexodus.desync.com%3A6969","seeders":0,"leechers":1,"uploader":"merzedes","files":-1,"time":1397604266,"description":"Bad Ass Wrestlers trap Noobes on the mat and finger fuck the fuck out of them\n\nApr 15, 2014 - Performers: Jayogen ,  Izamar Gutierrez ,  Sasha Princess Banks  and  Ella Nova  \n\n\nMed and HD MP4 + Pics.\n\n\nJayogen\n\n&quot;The Beast&quot; \nHeight:  5'6&quot; \nWeight:  145lbs \nSeason W/L:  (1 - 1)  \nLifetime W/L:  (1 - 1)  \n\n\nIzamar Gutierrez\n\n&quot;La Diabla&quot; \nHeight:  5'3&quot; \nWeight:  130lbs \nSeason W/L:  (1 - 1)  \nLifetime W/L:  (10 - 6)  \n\n\nSasha Princess Banks\n\n&quot;&quot; \nHeight:  5'3&quot; \nWeight:  130lbs \nSeason W/L:  ( - )  \nLifetime W/L:  (0 - 0)  \n\n\nThis is the first installment of Team Wrangler vs. Team Queen. The Queens DESTROYED the wranglers in the March Madness Submission in the Mission Match up but today the Wranglers are taking the reins for the season. \n\nParis Lincoln was Pink Carded out of the tournament do to an injury from the march madness tournament. Her replacement is Isamar Guiterrez. Ella Nova is the other team wrangler wrestling tonight. \n\nFor Team Queeen we have Jayogen who is taking Juliette March's place on Team Queen permanently. Sasha Princess Banks is the original Team Queen member wrestling for her team today. \n\nTeam Wrangler doesn't make good use of their tags. Their strategy is easy to see from the get go. They keep Izamar out to do all the wrestling. She's able to fight off Jayogen and Sasha for the first round but they start to wear her down. Each team takes advantage of the opposing rookie. Sasha and Ella are both trapped on the mats getting finger fucked to frustration. \n\nScreens &lt;a href=&quot;\nhttp://www.ultimatesurrender.com/site/shoot.jsp?shootId=35363&quot; rel=&quot;nofollow&quot; target=&quot;_NEW&quot;&gt;\nhttp://www.ultimatesurrender.com/site/shoot.jsp?shootId=35363&lt;/a&gt;\n\n14 000 down, but how much more to come ?? You decide ;) \n\nThe more you appreciate it, the more we want to do it. Can we get to 15k ??? \n\nWell, if you still like what Shallow2 and I upload, how about leaving us a nice comment below ? :)\n\n\nAny Questions ?? Read our FAQ!!\n &lt;a href=&quot;\nhttp://image.bayimg.com/eaea7e9e982a9a677d61e4f5aaf93b7643bd6eeb.jpg&quot; rel=&quot;nofollow&quot; target=&quot;_NEW&quot;&gt;\nhttp://image.bayimg.com/eaea7e9e982a9a677d61e4f5aaf93b7643bd6eeb.jpg&lt;/a&gt;\n\n\nCheers  :-)  \n\n","torrent":{"xt":"urn:btih:55c32c3a99e86ff37b9346de033e4277ec1766fe","amp;dn":"UltimateSurrender--US-35363+Jayogen%2C+Izamar+Gutierrez%2C+Sasha+Pri","amp;tr":["udp%3A%2F%2Ftracker.openbittorrent.com%3A80","udp%3A%2F%2Fopen.demonii.com%3A1337","udp%3A%2F%2Ftracker.coppersurfer.tk%3A6969","udp%3A%2F%2Fexodus.desync.com%3A6969"],"infoHash":"55c32c3a99e86ff37b9346de033e4277ec1766fe","infoHashBuffer":{"type":"Buffer","data":[85,195,44,58,153,232,111,243,123,147,70,222,3,62,66,119,236,23,102,254]},"announce":[],"urlList":[]}}