{"title":"Risa Kotani - Lewd Lady Wants Loads of Bukkake","uid":9877425,"size":5348404398,"categoryP":"porn","categoryS":"hd___movies","magnet":"?xt=urn:btih:5c4d2283eab7262d4d58fbbfdd0ff0f7d8be68ae&amp;dn=Risa+Kotani+-+Lewd+Lady+Wants+Loads+of+Bukkake&amp;tr=udp%3A%2F%2Ftracker.openbittorrent.com%3A80&amp;tr=udp%3A%2F%2Fopen.demonii.com%3A1337&amp;tr=udp%3A%2F%2Ftracker.coppersurfer.tk%3A6969&amp;tr=udp%3A%2F%2Fexodus.desync.com%3A6969","seeders":0,"leechers":2,"uploader":"cbill7","files":3,"time":1396490141,"description":"Risa Kotani - Lewd Lady Wants Loads of Bukkake BEB051 BEB-051\n1080p\n &lt;a href=&quot;\nhttp://bayimg.com/kanmFaAFE&quot; rel=&quot;nofollow&quot; target=&quot;_NEW&quot;&gt;\nhttp://bayimg.com/kanmFaAFE&lt;/a&gt; &lt;a href=&quot;\nhttp://bayimg.com/kaNMgAAFe&quot; rel=&quot;nofollow&quot; target=&quot;_NEW&quot;&gt;\nhttp://bayimg.com/kaNMgAAFe&lt;/a&gt; &lt;a href=&quot;\nhttp://bayimg.com/kaNmHAaFe&quot; rel=&quot;nofollow&quot; target=&quot;_NEW&quot;&gt;\nhttp://bayimg.com/kaNmHAaFe&lt;/a&gt;","torrent":{"xt":"urn:btih:5c4d2283eab7262d4d58fbbfdd0ff0f7d8be68ae","amp;dn":"Risa+Kotani+-+Lewd+Lady+Wants+Loads+of+Bukkake","amp;tr":["udp%3A%2F%2Ftracker.openbittorrent.com%3A80","udp%3A%2F%2Fopen.demonii.com%3A1337","udp%3A%2F%2Ftracker.coppersurfer.tk%3A6969","udp%3A%2F%2Fexodus.desync.com%3A6969"],"infoHash":"5c4d2283eab7262d4d58fbbfdd0ff0f7d8be68ae","infoHashBuffer":{"type":"Buffer","data":[92,77,34,131,234,183,38,45,77,88,251,191,221,15,240,247,216,190,104,174]},"announce":[],"urlList":[]}}