{"title":"trdrp19","uid":8509291,"size":1353856,"categoryP":"audio","categoryS":"other","magnet":"?xt=urn:btih:66823d4cfc352dc3175804634a7aeda7515b3aa1&amp;dn=trdrp19&amp;tr=udp%3A%2F%2Ftracker.openbittorrent.com%3A80&amp;tr=udp%3A%2F%2Fopen.demonii.com%3A1337&amp;tr=udp%3A%2F%2Ftracker.coppersurfer.tk%3A6969&amp;tr=udp%3A%2F%2Fexodus.desync.com%3A6969","seeders":0,"leechers":0,"uploader":"cariez7","files":1,"time":1369521759,"description":"trdrp19","torrent":{"xt":"urn:btih:66823d4cfc352dc3175804634a7aeda7515b3aa1","amp;dn":"trdrp19","amp;tr":["udp%3A%2F%2Ftracker.openbittorrent.com%3A80","udp%3A%2F%2Fopen.demonii.com%3A1337","udp%3A%2F%2Ftracker.coppersurfer.tk%3A6969","udp%3A%2F%2Fexodus.desync.com%3A6969"],"infoHash":"66823d4cfc352dc3175804634a7aeda7515b3aa1","infoHashBuffer":{"type":"Buffer","data":[102,130,61,76,252,53,45,195,23,88,4,99,74,122,237,167,81,91,58,161]},"announce":[],"urlList":[]}}