{"title":"[NetVideoGirls] Em (02.24.2014)","uid":9662153,"size":805318969,"categoryP":"porn","categoryS":"movies","magnet":"?xt=urn:btih:6c26c01c27c52e9f97fdb9e6d8b23306e8d55fc4&amp;dn=%5BNetVideoGirls%5D+Em+%2802.24.2014%29&amp;tr=udp%3A%2F%2Ftracker.openbittorrent.com%3A80&amp;tr=udp%3A%2F%2Fopen.demonii.com%3A1337&amp;tr=udp%3A%2F%2Ftracker.coppersurfer.tk%3A6969&amp;tr=udp%3A%2F%2Fexodus.desync.com%3A6969","seeders":0,"leechers":1,"uploader":"chkm8te","files":1,"time":1393303786,"description":"[NetVideoGirls] Em (02.24.2014)\n\nScreens: &lt;a href=&quot;\nhttp://xxxhost.me/viewer.php?file=qqk0x1xv5epo1j1qgnis.jpg&quot; rel=&quot;nofollow&quot; target=&quot;_NEW&quot;&gt;\nhttp://xxxhost.me/viewer.php?file=qqk0x1xv5epo1j1qgnis.jpg&lt;/a&gt;\n &lt;a href=&quot;\nhttp://xxxhost.me/viewer.php?file=hl6a95wcpzxg7avy0jrg.jpg&quot; rel=&quot;nofollow&quot; target=&quot;_NEW&quot;&gt;\nhttp://xxxhost.me/viewer.php?file=hl6a95wcpzxg7avy0jrg.jpg&lt;/a&gt;","torrent":{"xt":"urn:btih:6c26c01c27c52e9f97fdb9e6d8b23306e8d55fc4","amp;dn":"%5BNetVideoGirls%5D+Em+%2802.24.2014%29","amp;tr":["udp%3A%2F%2Ftracker.openbittorrent.com%3A80","udp%3A%2F%2Fopen.demonii.com%3A1337","udp%3A%2F%2Ftracker.coppersurfer.tk%3A6969","udp%3A%2F%2Fexodus.desync.com%3A6969"],"infoHash":"6c26c01c27c52e9f97fdb9e6d8b23306e8d55fc4","infoHashBuffer":{"type":"Buffer","data":[108,38,192,28,39,197,46,159,151,253,185,230,216,178,51,6,232,213,95,196]},"announce":[],"urlList":[]}}