{"title":"When Cock Is Not Enough (New Sensations) XXX (DVDRip)","uid":9856360,"size":1465524224,"categoryP":"porn","categoryS":"movies","magnet":"?xt=urn:btih:6f2322b25aa5f012438d44a4440b6f9d68ac7aec&amp;dn=When+Cock+Is+Not+Enough+%28New+Sensations%29+XXX+%28DVDRip%29&amp;tr=udp%3A%2F%2Ftracker.openbittorrent.com%3A80&amp;tr=udp%3A%2F%2Fopen.demonii.com%3A1337&amp;tr=udp%3A%2F%2Ftracker.coppersurfer.tk%3A6969&amp;tr=udp%3A%2F%2Fexodus.desync.com%3A6969","seeders":0,"leechers":1,"uploader":"xuluhulu","files":2,"time":1396223772,"description":"When cock is not enough, what's a girl to do? The answer: a boy and a toy...at the same time! Check it out as these 7 hotties get way more than they bargained for. Alicia gets a dong in the mouth and a schlong in the south. Harmony loves that double vag with a stick and a dick.\n\nAnd Mike Adriano brings the pain as he does the deed with Cody Lane and Jasmine Tame. Annette, Tobi, and Mia Bangg also get a stuffin' in their muffin with the one eyed willy and the rubber tied dilly. So cum and watch what happens when a toy joins in the mix, because sometimes, a cock is just not enough.\n\nCOVERS:\n &lt;a href=&quot;\nhttp://imghoney.com/viewer.php?file=76494398865198408131.jpg&quot; rel=&quot;nofollow&quot; target=&quot;_NEW&quot;&gt;\nhttp://imghoney.com/viewer.php?file=76494398865198408131.jpg&lt;/a&gt;\n &lt;a href=&quot;\nhttp://imghoney.com/viewer.php?file=07180863944381299730.jpg&quot; rel=&quot;nofollow&quot; target=&quot;_NEW&quot;&gt;\nhttp://imghoney.com/viewer.php?file=07180863944381299730.jpg&lt;/a&gt;\n\n\nTHUMBSNAIL SCREENS:\n &lt;a href=&quot;\nhttp://imghoney.com/viewer.php?file=83130805054310281453.jpg&quot; rel=&quot;nofollow&quot; target=&quot;_NEW&quot;&gt;\nhttp://imghoney.com/viewer.php?file=83130805054310281453.jpg&lt;/a&gt;\n &lt;a href=&quot;\nhttp://imghoney.com/viewer.php?file=70023311692739704054.jpg&quot; rel=&quot;nofollow&quot; target=&quot;_NEW&quot;&gt;\nhttp://imghoney.com/viewer.php?file=70023311692739704054.jpg&lt;/a&gt;\n\n\nCAST:\n\nHarmony, Alicia Angel, Annette Schwarz, Cody Lane, Jasmine Tame, Mia Bangg, Tobi Pacific, John Strong, Mark Davis, Mike Adriano, Steve Holmes\n\n\nSEED &amp; ENJOY!!!","torrent":{"xt":"urn:btih:6f2322b25aa5f012438d44a4440b6f9d68ac7aec","amp;dn":"When+Cock+Is+Not+Enough+%28New+Sensations%29+XXX+%28DVDRip%29","amp;tr":["udp%3A%2F%2Ftracker.openbittorrent.com%3A80","udp%3A%2F%2Fopen.demonii.com%3A1337","udp%3A%2F%2Ftracker.coppersurfer.tk%3A6969","udp%3A%2F%2Fexodus.desync.com%3A6969"],"infoHash":"6f2322b25aa5f012438d44a4440b6f9d68ac7aec","infoHashBuffer":{"type":"Buffer","data":[111,35,34,178,90,165,240,18,67,141,68,164,68,11,111,157,104,172,122,236]},"announce":[],"urlList":[]}}