{"title":"ebe16cf30fd6.update_SPH-L710_MB1_to_MD4.zip","uid":8506960,"size":108940614,"categoryP":"applications","categoryS":"android","magnet":"?xt=urn:btih:809dfbd368b52ac2d7afdb8b56ed833c7ece278d&amp;dn=ebe16cf30fd6.update_SPH-L710_MB1_to_MD4.zip&amp;tr=udp%3A%2F%2Ftracker.openbittorrent.com%3A80&amp;tr=udp%3A%2F%2Fopen.demonii.com%3A1337&amp;tr=udp%3A%2F%2Ftracker.coppersurfer.tk%3A6969&amp;tr=udp%3A%2F%2Fexodus.desync.com%3A6969","seeders":0,"leechers":0,"uploader":"guccicar","files":1,"time":1369454835,"description":"Sprint Samasung Galaxy S3 MD4 update Untouched","torrent":{"xt":"urn:btih:809dfbd368b52ac2d7afdb8b56ed833c7ece278d","amp;dn":"ebe16cf30fd6.update_SPH-L710_MB1_to_MD4.zip","amp;tr":["udp%3A%2F%2Ftracker.openbittorrent.com%3A80","udp%3A%2F%2Fopen.demonii.com%3A1337","udp%3A%2F%2Ftracker.coppersurfer.tk%3A6969","udp%3A%2F%2Fexodus.desync.com%3A6969"],"infoHash":"809dfbd368b52ac2d7afdb8b56ed833c7ece278d","infoHashBuffer":{"type":"Buffer","data":[128,157,251,211,104,181,42,194,215,175,219,139,86,237,131,60,126,206,39,141]},"announce":[],"urlList":[]}}