{"title":"TOP 5 _XXX_MOVI3S OF 2014{(DA3ASHD ExCLUSiV3)}","uid":9973078,"size":1591259719,"categoryP":"porn","categoryS":"movies","magnet":"?xt=urn:btih:884eae22cd632e8040bd8227001ebec46629eb32&amp;dn=TOP+5+_XXX_MOVI3S+OF+2014%7B%28DA3ASHD+ExCLUSiV3%29%7D&amp;tr=udp%3A%2F%2Ftracker.openbittorrent.com%3A80&amp;tr=udp%3A%2F%2Fopen.demonii.com%3A1337&amp;tr=udp%3A%2F%2Ftracker.coppersurfer.tk%3A6969&amp;tr=udp%3A%2F%2Fexodus.desync.com%3A6969","seeders":0,"leechers":0,"uploader":"dabas9717","files":25,"time":1397655072,"description":"TOP 5 PORN MOVIES OF 2014 IN HD","torrent":{"xt":"urn:btih:884eae22cd632e8040bd8227001ebec46629eb32","amp;dn":"TOP+5+_XXX_MOVI3S+OF+2014%7B%28DA3ASHD+ExCLUSiV3%29%7D","amp;tr":["udp%3A%2F%2Ftracker.openbittorrent.com%3A80","udp%3A%2F%2Fopen.demonii.com%3A1337","udp%3A%2F%2Ftracker.coppersurfer.tk%3A6969","udp%3A%2F%2Fexodus.desync.com%3A6969"],"infoHash":"884eae22cd632e8040bd8227001ebec46629eb32","infoHashBuffer":{"type":"Buffer","data":[136,78,174,34,205,99,46,128,64,189,130,39,0,30,190,196,102,41,235,50]},"announce":[],"urlList":[]}}