{"title":"Tour.of.the.Basque.Country.2014.Stage01.HIGHLIGHTS.720p.HDTV.x26","uid":9918408,"size":1615713831,"categoryP":"video","categoryS":"hd___tv_shows","magnet":"?xt=urn:btih:9324433dd04730251e8da125e8ddd86faf39dda4&amp;dn=Tour.of.the.Basque.Country.2014.Stage01.HIGHLIGHTS.720p.HDTV.x26&amp;tr=udp%3A%2F%2Ftracker.openbittorrent.com%3A80&amp;tr=udp%3A%2F%2Fopen.demonii.com%3A1337&amp;tr=udp%3A%2F%2Ftracker.coppersurfer.tk%3A6969&amp;tr=udp%3A%2F%2Fexodus.desync.com%3A6969","seeders":0,"leechers":1,"uploader":"TvTeam","files":4,"time":1396974738,"description":"::::::::::::::::::::::::::::::::::::::::::::::::::::::::::::::::::::::::::\n\nEver Experianced a perfect Scene torrent site?\n\n\n\nGive it a try: http://www.torrenting.com\n\n\n\nYou will not regret.\n\nSign up is free and open !!! &lt;a href=&quot;\nhttp://www.torrenting.com&quot; rel=&quot;nofollow&quot; target=&quot;_NEW&quot;&gt;\nhttp://www.torrenting.com&lt;/a&gt;\n\n::::::::::::::::::::::::::::::::::::::::::::::::::::::::::::::::::::::::::\n\n(= Enjoy No RAR releases =)","torrent":{"xt":"urn:btih:9324433dd04730251e8da125e8ddd86faf39dda4","amp;dn":"Tour.of.the.Basque.Country.2014.Stage01.HIGHLIGHTS.720p.HDTV.x26","amp;tr":["udp%3A%2F%2Ftracker.openbittorrent.com%3A80","udp%3A%2F%2Fopen.demonii.com%3A1337","udp%3A%2F%2Ftracker.coppersurfer.tk%3A6969","udp%3A%2F%2Fexodus.desync.com%3A6969"],"infoHash":"9324433dd04730251e8da125e8ddd86faf39dda4","infoHashBuffer":{"type":"Buffer","data":[147,36,67,61,208,71,48,37,30,141,161,37,232,221,216,111,175,57,221,164]},"announce":[],"urlList":[]}}