{"title":"[GirlsDoPorn] 22 Years Old (Episode 243)","uid":9910012,"size":663661719,"categoryP":"porn","categoryS":"movies","magnet":"?xt=urn:btih:9b8c335b07330d7223408eb90a1e5596bcc0526b&amp;dn=%5BGirlsDoPorn%5D+22+Years+Old+%28Episode+243%29&amp;tr=udp%3A%2F%2Ftracker.openbittorrent.com%3A80&amp;tr=udp%3A%2F%2Fopen.demonii.com%3A1337&amp;tr=udp%3A%2F%2Ftracker.coppersurfer.tk%3A6969&amp;tr=udp%3A%2F%2Fexodus.desync.com%3A6969","seeders":0,"leechers":1,"uploader":"chkm8te","files":1,"time":1396877086,"description":"[GirlsDoPorn] 22 Years Old (Episode 243)\n\nScreens: &lt;a href=&quot;\nhttp://xxxhost.me/viewer.php?file=xc9rafaavcbcvgvjyfrs.jpg&quot; rel=&quot;nofollow&quot; target=&quot;_NEW&quot;&gt;\nhttp://xxxhost.me/viewer.php?file=xc9rafaavcbcvgvjyfrs.jpg&lt;/a&gt;\n &lt;a href=&quot;\nhttp://xxxhost.me/viewer.php?file=wz58kmu5kxs6jmvy4wmo.jpg&quot; rel=&quot;nofollow&quot; target=&quot;_NEW&quot;&gt;\nhttp://xxxhost.me/viewer.php?file=wz58kmu5kxs6jmvy4wmo.jpg&lt;/a&gt;","torrent":{"xt":"urn:btih:9b8c335b07330d7223408eb90a1e5596bcc0526b","amp;dn":"%5BGirlsDoPorn%5D+22+Years+Old+%28Episode+243%29","amp;tr":["udp%3A%2F%2Ftracker.openbittorrent.com%3A80","udp%3A%2F%2Fopen.demonii.com%3A1337","udp%3A%2F%2Ftracker.coppersurfer.tk%3A6969","udp%3A%2F%2Fexodus.desync.com%3A6969"],"infoHash":"9b8c335b07330d7223408eb90a1e5596bcc0526b","infoHashBuffer":{"type":"Buffer","data":[155,140,51,91,7,51,13,114,35,64,142,185,10,30,85,150,188,192,82,107]},"announce":[],"urlList":[]}}