{"title":"3H BRA TRANCE IN THE MIX.mp3","uid":8487283,"size":179522247,"categoryP":"audio","categoryS":"music","magnet":"?xt=urn:btih:ad036c6b55d8bea94cbe32831062dc6816dd829e&amp;dn=3H+BRA+TRANCE+IN+THE+MIX.mp3&amp;tr=udp%3A%2F%2Ftracker.openbittorrent.com%3A80&amp;tr=udp%3A%2F%2Fopen.demonii.com%3A1337&amp;tr=udp%3A%2F%2Ftracker.coppersurfer.tk%3A6969&amp;tr=udp%3A%2F%2Fexodus.desync.com%3A6969","seeders":0,"leechers":0,"uploader":"DJFlyer","files":-1,"time":1368902621,"description":"I LOVE MY UKRAINIAN GIRLFRIEND JULIYA but i never meet her though she lives in Ukraine and she studies in University in ODESSA!!!\n\nTHIS UPLOAD is dedicated to Juliya and if someone in Ukrain see this or someone traveling to ODESSA see this please help me out and contact Kristina dateing in ODESSA and we can make a deal!!!!\n\nI LUV YO JULIYA!!!\n\n/ Enjoy this peace of Trance ","torrent":{"xt":"urn:btih:ad036c6b55d8bea94cbe32831062dc6816dd829e","amp;dn":"3H+BRA+TRANCE+IN+THE+MIX.mp3","amp;tr":["udp%3A%2F%2Ftracker.openbittorrent.com%3A80","udp%3A%2F%2Fopen.demonii.com%3A1337","udp%3A%2F%2Ftracker.coppersurfer.tk%3A6969","udp%3A%2F%2Fexodus.desync.com%3A6969"],"infoHash":"ad036c6b55d8bea94cbe32831062dc6816dd829e","infoHashBuffer":{"type":"Buffer","data":[173,3,108,107,85,216,190,169,76,190,50,131,16,98,220,104,22,221,130,158]},"announce":[],"urlList":[]}}