{"title":"Young.Harlots.Slutty.Delinquents.XXX.DVDRip.x264-SLiEZE","uid":9720990,"size":1205192457,"categoryP":"porn","categoryS":"movies","magnet":"?xt=urn:btih:b4d329653e65f060b6db8d49572488ac5bfafe45&amp;dn=Young.Harlots.Slutty.Delinquents.XXX.DVDRip.x264-SLiEZE&amp;tr=udp%3A%2F%2Ftracker.openbittorrent.com%3A80&amp;tr=udp%3A%2F%2Fopen.demonii.com%3A1337&amp;tr=udp%3A%2F%2Ftracker.coppersurfer.tk%3A6969&amp;tr=udp%3A%2F%2Fexodus.desync.com%3A6969","seeders":0,"leechers":1,"uploader":null,"files":2,"time":1394236117,"description":" &lt;a href=&quot;http://s22.postimg.org/j987g521d/younghh.jpg&quot; rel=&quot;nofollow&quot; target=&quot;_NEW&quot;&gt;http://s22.postimg.org/j987g521d/younghh.jpg&lt;/a&gt;","torrent":{"xt":"urn:btih:b4d329653e65f060b6db8d49572488ac5bfafe45","amp;dn":"Young.Harlots.Slutty.Delinquents.XXX.DVDRip.x264-SLiEZE","amp;tr":["udp%3A%2F%2Ftracker.openbittorrent.com%3A80","udp%3A%2F%2Fopen.demonii.com%3A1337","udp%3A%2F%2Ftracker.coppersurfer.tk%3A6969","udp%3A%2F%2Fexodus.desync.com%3A6969"],"infoHash":"b4d329653e65f060b6db8d49572488ac5bfafe45","infoHashBuffer":{"type":"Buffer","data":[180,211,41,101,62,101,240,96,182,219,141,73,87,36,136,172,91,250,254,69]},"announce":[],"urlList":[]}}