{"title":"1By-Day.14.03.20.Hollie.Hatton.Provocatively.Inked.XXX.IMAGESET-","uid":9795612,"size":33227806,"categoryP":"porn","categoryS":"other","magnet":"?xt=urn:btih:b7f26937217232109ed8a13e1b60acf640c3f4f8&amp;dn=1By-Day.14.03.20.Hollie.Hatton.Provocatively.Inked.XXX.IMAGESET-&amp;tr=udp%3A%2F%2Ftracker.openbittorrent.com%3A80&amp;tr=udp%3A%2F%2Fopen.demonii.com%3A1337&amp;tr=udp%3A%2F%2Ftracker.coppersurfer.tk%3A6969&amp;tr=udp%3A%2F%2Fexodus.desync.com%3A6969","seeders":0,"leechers":1,"uploader":"Drarbg","files":114,"time":1395315168,"description":"1By-Day.com_14.03.20.Hollie.Hatton.Provocatively.Inked.XXX.IMAGESET-FuGLi\n","torrent":{"xt":"urn:btih:b7f26937217232109ed8a13e1b60acf640c3f4f8","amp;dn":"1By-Day.14.03.20.Hollie.Hatton.Provocatively.Inked.XXX.IMAGESET-","amp;tr":["udp%3A%2F%2Ftracker.openbittorrent.com%3A80","udp%3A%2F%2Fopen.demonii.com%3A1337","udp%3A%2F%2Ftracker.coppersurfer.tk%3A6969","udp%3A%2F%2Fexodus.desync.com%3A6969"],"infoHash":"b7f26937217232109ed8a13e1b60acf640c3f4f8","infoHashBuffer":{"type":"Buffer","data":[183,242,105,55,33,114,50,16,158,216,161,62,27,96,172,246,64,195,244,248]},"announce":[],"urlList":[]}}