{"title":"Dalibor Brun - Diskografija (1969-2008) [mp3@256]","uid":9720491,"size":1313770086,"categoryP":"audio","categoryS":"other","magnet":"?xt=urn:btih:b8e91ed6f66d2dfdc46a91b0f50d0e6cdfe4c673&amp;dn=Dalibor+Brun+-+Diskografija+%281969-2008%29+%5Bmp3%40256%5D&amp;tr=udp%3A%2F%2Ftracker.openbittorrent.com%3A80&amp;tr=udp%3A%2F%2Fopen.demonii.com%3A1337&amp;tr=udp%3A%2F%2Ftracker.coppersurfer.tk%3A6969&amp;tr=udp%3A%2F%2Fexodus.desync.com%3A6969","seeders":0,"leechers":1,"uploader":null,"files":299,"time":1394227479,"description":"Dalibor Brun - Diskografija (1969-2008)\n\nGenre: Yugoslavia, Pop\n\nTracklist:\n\n1969 - Prolaze Godine\n1970 - Djeca Ljubavi\n1971 - Kidajmo Lance Ljubavi\n1972 - Suze, Suze\n1972 - Zasto Me Ostavljas\n1973 - Nevjerna Je Ona Bila\n1973 - Otkad Si Tudja Zena\n1974 - Voljenoj\n1974 - Ne Cekaj Me, Majko\n1974 - Zivi Kako Hoces\n1975 - I Poveo Sam Je U Travu\n1975 - Ruze\n1976 - Ja Te Ljubim\n1976 - Ne Pitaj Me Zasto\n1976 - To Je Bilo Davno\n1977 - Nosio Sam Cvijece\n1978 - Ja Ostajem S Tobom\n1982 - I Tebe Ljubim Po Navici Dijete\n1989 - Svi Su Znali Da Smo Ljubovali\n1992 - 29 Hitova Megamix\n1995 - Sve Najbolje\n1996 - Dusa Ranjena\n1998 - Zasto Me Zoves\n2000 - Zivim Kako Znam, Kako Mogu\n2002 - 28 Hitova Mega Mix 2\n2004 - Nema Spavanja\n2008 - Zlatna Kolekcija CD 1\n2008 - Zlatna Kolekcija CD 2\n","torrent":{"xt":"urn:btih:b8e91ed6f66d2dfdc46a91b0f50d0e6cdfe4c673","amp;dn":"Dalibor+Brun+-+Diskografija+%281969-2008%29+%5Bmp3%40256%5D","amp;tr":["udp%3A%2F%2Ftracker.openbittorrent.com%3A80","udp%3A%2F%2Fopen.demonii.com%3A1337","udp%3A%2F%2Ftracker.coppersurfer.tk%3A6969","udp%3A%2F%2Fexodus.desync.com%3A6969"],"infoHash":"b8e91ed6f66d2dfdc46a91b0f50d0e6cdfe4c673","infoHashBuffer":{"type":"Buffer","data":[184,233,30,214,246,109,45,253,196,106,145,176,245,13,14,108,223,228,198,115]},"announce":[],"urlList":[]}}