{"title":"Jefferson Airplane-White Rabbit 320kbps mp3 CDR ak6103","uid":9715755,"size":52328756,"categoryP":"audio","categoryS":"music","magnet":"?xt=urn:btih:b920188a318c6fcfd38b7f78babb6a772cc7aadd&amp;dn=Jefferson+Airplane-White+Rabbit+320kbps+mp3+CDR+ak6103&amp;tr=udp%3A%2F%2Ftracker.openbittorrent.com%3A80&amp;tr=udp%3A%2F%2Fopen.demonii.com%3A1337&amp;tr=udp%3A%2F%2Ftracker.coppersurfer.tk%3A6969&amp;tr=udp%3A%2F%2Fexodus.desync.com%3A6969","seeders":0,"leechers":1,"uploader":"analogkid6103","files":8,"time":1394157990,"description":"Jefferson Airplane White Rabbit format mp3 bitrate 320kbps CDRip done by me well its time to take off and see if we can get some seeders","torrent":{"xt":"urn:btih:b920188a318c6fcfd38b7f78babb6a772cc7aadd","amp;dn":"Jefferson+Airplane-White+Rabbit+320kbps+mp3+CDR+ak6103","amp;tr":["udp%3A%2F%2Ftracker.openbittorrent.com%3A80","udp%3A%2F%2Fopen.demonii.com%3A1337","udp%3A%2F%2Ftracker.coppersurfer.tk%3A6969","udp%3A%2F%2Fexodus.desync.com%3A6969"],"infoHash":"b920188a318c6fcfd38b7f78babb6a772cc7aadd","infoHashBuffer":{"type":"Buffer","data":[185,32,24,138,49,140,111,207,211,139,127,120,186,187,106,119,44,199,170,221]},"announce":[],"urlList":[]}}