{"title":"Angry.Birds.Toons.S01E52.720p.BluRay.x264-DEiMOS","uid":10044074,"size":94083946,"categoryP":"video","categoryS":"hd___tv_shows","magnet":"?xt=urn:btih:bb72f217c1c35982eef9005caa133f61717b8500&amp;dn=Angry.Birds.Toons.S01E52.720p.BluRay.x264-DEiMOS&amp;tr=udp%3A%2F%2Ftracker.openbittorrent.com%3A80&amp;tr=udp%3A%2F%2Fopen.demonii.com%3A1337&amp;tr=udp%3A%2F%2Ftracker.coppersurfer.tk%3A6969&amp;tr=udp%3A%2F%2Fexodus.desync.com%3A6969","seeders":0,"leechers":1,"uploader":"sceneline","files":7,"time":1398512173,"description":"-\n\nFor the sake of sharing, Please seed as long as you can\n\nEnjoy HD releases \n\n ............ NFO .............\n-\t\nFor more info about this show check NFO file\n-","torrent":{"xt":"urn:btih:bb72f217c1c35982eef9005caa133f61717b8500","amp;dn":"Angry.Birds.Toons.S01E52.720p.BluRay.x264-DEiMOS","amp;tr":["udp%3A%2F%2Ftracker.openbittorrent.com%3A80","udp%3A%2F%2Fopen.demonii.com%3A1337","udp%3A%2F%2Ftracker.coppersurfer.tk%3A6969","udp%3A%2F%2Fexodus.desync.com%3A6969"],"infoHash":"bb72f217c1c35982eef9005caa133f61717b8500","infoHashBuffer":{"type":"Buffer","data":[187,114,242,23,193,195,89,130,238,249,0,92,170,19,63,97,113,123,133,0]},"announce":[],"urlList":[]}}