{"title":"Third Degree - Young Thighs In Knee Highs 4","uid":9853524,"size":1815860263,"categoryP":"porn","categoryS":"movies","magnet":"?xt=urn:btih:c49bec8c10f39989a70d541032eb8b094a301c49&amp;dn=Third+Degree+-+Young+Thighs+In+Knee+Highs+4&amp;tr=udp%3A%2F%2Ftracker.openbittorrent.com%3A80&amp;tr=udp%3A%2F%2Fopen.demonii.com%3A1337&amp;tr=udp%3A%2F%2Ftracker.coppersurfer.tk%3A6969&amp;tr=udp%3A%2F%2Fexodus.desync.com%3A6969","seeders":0,"leechers":3,"uploader":"irealu69","files":-1,"time":1396190084,"description":"Third Degree - Young Thighs In Knee Highs 4\n~~~~~~~~~~~~~~~~~~~~~~~~~~~~~~~~~~~~~~~~~~~\n\nScreenshots:\n~~~~~~~~~~~~\n &lt;a href=&quot;\nhttp://picturescream.com/x/clean/foBI&quot; rel=&quot;nofollow&quot; target=&quot;_NEW&quot;&gt;\nhttp://picturescream.com/x/clean/foBI&lt;/a&gt;\n &lt;a href=&quot;\nhttp://picturescream.com/x/clean/foBt&quot; rel=&quot;nofollow&quot; target=&quot;_NEW&quot;&gt;\nhttp://picturescream.com/x/clean/foBt&lt;/a&gt;\n &lt;a href=&quot;\nhttp://picturescream.com/x/clean/foBy&quot; rel=&quot;nofollow&quot; target=&quot;_NEW&quot;&gt;\nhttp://picturescream.com/x/clean/foBy&lt;/a&gt;\n &lt;a href=&quot;\nhttp://picturescream.com/x/clean/foBz&quot; rel=&quot;nofollow&quot; target=&quot;_NEW&quot;&gt;\nhttp://picturescream.com/x/clean/foBz&lt;/a&gt;\n &lt;a href=&quot;\nhttp://picturescream.com/x/clean/foBL&quot; rel=&quot;nofollow&quot; target=&quot;_NEW&quot;&gt;\nhttp://picturescream.com/x/clean/foBL&lt;/a&gt;\n\n\nVideos Info:\n~~~~~~~~~~~~\nSize: 1.69 GB\nResolution: 720x404","torrent":{"xt":"urn:btih:c49bec8c10f39989a70d541032eb8b094a301c49","amp;dn":"Third+Degree+-+Young+Thighs+In+Knee+Highs+4","amp;tr":["udp%3A%2F%2Ftracker.openbittorrent.com%3A80","udp%3A%2F%2Fopen.demonii.com%3A1337","udp%3A%2F%2Ftracker.coppersurfer.tk%3A6969","udp%3A%2F%2Fexodus.desync.com%3A6969"],"infoHash":"c49bec8c10f39989a70d541032eb8b094a301c49","infoHashBuffer":{"type":"Buffer","data":[196,155,236,140,16,243,153,137,167,13,84,16,50,235,139,9,74,48,28,73]},"announce":[],"urlList":[]}}