{"title":"Hustlers.Girl.on.Girl.Oil.XXX.DVDRip.x264-CHiKANi","uid":8421980,"size":969382481,"categoryP":"porn","categoryS":"movies","magnet":"?xt=urn:btih:c7a750eea3ce21de5119e637c39dafcfc7baf1de&amp;dn=Hustlers.Girl.on.Girl.Oil.XXX.DVDRip.x264-CHiKANi&amp;tr=udp%3A%2F%2Ftracker.openbittorrent.com%3A80&amp;tr=udp%3A%2F%2Fopen.demonii.com%3A1337&amp;tr=udp%3A%2F%2Ftracker.coppersurfer.tk%3A6969&amp;tr=udp%3A%2F%2Fexodus.desync.com%3A6969","seeders":0,"leechers":0,"uploader":"R0thschild","files":2,"time":1367221900,"description":"--------------------------------------------\nGallery:  &lt;a href=&quot;\nhttp://publichash.com/index.php?page=torrent-details&amp;id=c7a750eea3ce21de5119e637c39dafcfc7baf1de&quot; rel=&quot;nofollow&quot; target=&quot;_NEW&quot;&gt;\nhttp://publichash.com/index.php?page=torrent-details&amp;id=c7a750eea3ce21de5119e637c39dafcfc7baf1de&lt;/a&gt;\n \nStudio\nHustler\nStarring\nKiera King, Jeanie Marie, Jennifer White, Sasha Heart, Christie Stevens, Lia Lor, Rikki Six, Jordana Heat\nGenre\nMasturbation\n\n--------------------------------------------","torrent":{"xt":"urn:btih:c7a750eea3ce21de5119e637c39dafcfc7baf1de","amp;dn":"Hustlers.Girl.on.Girl.Oil.XXX.DVDRip.x264-CHiKANi","amp;tr":["udp%3A%2F%2Ftracker.openbittorrent.com%3A80","udp%3A%2F%2Fopen.demonii.com%3A1337","udp%3A%2F%2Ftracker.coppersurfer.tk%3A6969","udp%3A%2F%2Fexodus.desync.com%3A6969"],"infoHash":"c7a750eea3ce21de5119e637c39dafcfc7baf1de","infoHashBuffer":{"type":"Buffer","data":[199,167,80,238,163,206,33,222,81,25,230,55,195,157,175,207,199,186,241,222]},"announce":[],"urlList":[]}}