{"title":"EroticBeauty - Irtemia Presenting Irtemia","uid":9889334,"size":39185544,"categoryP":"porn","categoryS":"pictures","magnet":"?xt=urn:btih:d71b6445d3d87cd5331c1e035d4ba356ddd1c7fa&amp;dn=EroticBeauty+-+Irtemia+Presenting+Irtemia&amp;tr=udp%3A%2F%2Ftracker.openbittorrent.com%3A80&amp;tr=udp%3A%2F%2Fopen.demonii.com%3A1337&amp;tr=udp%3A%2F%2Ftracker.coppersurfer.tk%3A6969&amp;tr=udp%3A%2F%2Fexodus.desync.com%3A6969","seeders":0,"leechers":1,"uploader":null,"files":33,"time":1396623846,"description":"pics ---\n\n &lt;a href=&quot;\nhttp://imghorny.biz/share-6B4E_533E19F9.html&quot; rel=&quot;nofollow&quot; target=&quot;_NEW&quot;&gt;\nhttp://imghorny.biz/share-6B4E_533E19F9.html&lt;/a&gt;\n\n &lt;a href=&quot;\nhttp://imghorny.biz/share-3354_533E1A6C.html&quot; rel=&quot;nofollow&quot; target=&quot;_NEW&quot;&gt;\nhttp://imghorny.biz/share-3354_533E1A6C.html&lt;/a&gt;","torrent":{"xt":"urn:btih:d71b6445d3d87cd5331c1e035d4ba356ddd1c7fa","amp;dn":"EroticBeauty+-+Irtemia+Presenting+Irtemia","amp;tr":["udp%3A%2F%2Ftracker.openbittorrent.com%3A80","udp%3A%2F%2Fopen.demonii.com%3A1337","udp%3A%2F%2Ftracker.coppersurfer.tk%3A6969","udp%3A%2F%2Fexodus.desync.com%3A6969"],"infoHash":"d71b6445d3d87cd5331c1e035d4ba356ddd1c7fa","infoHashBuffer":{"type":"Buffer","data":[215,27,100,69,211,216,124,213,51,28,30,3,93,75,163,86,221,209,199,250]},"announce":[],"urlList":[]}}