{"title":"One Finger Death Waltz 1.08","uid":9739390,"size":16572390,"categoryP":"games","categoryS":"android","magnet":"?xt=urn:btih:e133cc07f618f0622cfdfd116f06e69c2c9c51b7&amp;dn=One+Finger+Death+Waltz+1.08&amp;tr=udp%3A%2F%2Ftracker.openbittorrent.com%3A80&amp;tr=udp%3A%2F%2Fopen.demonii.com%3A1337&amp;tr=udp%3A%2F%2Ftracker.coppersurfer.tk%3A6969&amp;tr=udp%3A%2F%2Fexodus.desync.com%3A6969","seeders":0,"leechers":0,"uploader":"hicalwiz","files":-1,"time":1394485858,"description":"A shmup score attack for android devices\n\n*FB-support (this version)\n*Completely free (no in-app purchases)\n*Excellent controls\n*Intense arcadey action\n*Sweet pixel graphics\n\n\nGoogle play version (achievements and leaderboard:\n &lt;a href=&quot;\nhttps://play.google.com/store/apps/details?id=com.highcalibrewizard.onefingerdeathwaltz&amp;hl=en&quot; rel=&quot;nofollow&quot; target=&quot;_NEW&quot;&gt;\nhttps://play.google.com/store/apps/details?id=com.highcalibrewizard.onefingerdeathwaltz&amp;hl=en&lt;/a&gt;\n\nPlease help vote this game up, on Google, if you approve.\n\n\nAnother of my shmups (for windows): &lt;a href=&quot;\nhttp://thepiratebay.se/torrent/9720783/Attack_of_the_Crimson_Marauders&quot; rel=&quot;nofollow&quot; target=&quot;_NEW&quot;&gt;\nhttp://thepiratebay.se/torrent/9720783/Attack_of_the_Crimson_Marauders&lt;/a&gt;","torrent":{"xt":"urn:btih:e133cc07f618f0622cfdfd116f06e69c2c9c51b7","amp;dn":"One+Finger+Death+Waltz+1.08","amp;tr":["udp%3A%2F%2Ftracker.openbittorrent.com%3A80","udp%3A%2F%2Fopen.demonii.com%3A1337","udp%3A%2F%2Ftracker.coppersurfer.tk%3A6969","udp%3A%2F%2Fexodus.desync.com%3A6969"],"infoHash":"e133cc07f618f0622cfdfd116f06e69c2c9c51b7","infoHashBuffer":{"type":"Buffer","data":[225,51,204,7,246,24,240,98,44,253,253,17,111,6,230,156,44,156,81,183]},"announce":[],"urlList":[]}}