{"title":"Let's Do Something Exciting, Baby. Let's Share Our Sexlife Onlin","uid":9889122,"size":24126196,"categoryP":"porn","categoryS":"movie_clips","magnet":"?xt=urn:btih:e9f2dd2d0c2ff90c8db23a64252383c951dd2c65&amp;dn=Let%27s+Do+Something+Exciting%2C+Baby.+Let%27s+Share+Our+Sexlife+Onlin&amp;tr=udp%3A%2F%2Ftracker.openbittorrent.com%3A80&amp;tr=udp%3A%2F%2Fopen.demonii.com%3A1337&amp;tr=udp%3A%2F%2Ftracker.coppersurfer.tk%3A6969&amp;tr=udp%3A%2F%2Fexodus.desync.com%3A6969","seeders":0,"leechers":0,"uploader":"mrdrake96","files":1,"time":1396619999,"description":"Let's Do Something Exciting, Baby. Let's Share Our Sexlife Online, But Blur Out Our Faces. Can't Wait To See Comments On My Fuck Skills !!!\n\nVideo codec: H264 (can be found in the latest k-lite codec pack)\nAudio codec: MPEG-2 Layer 3\nFormat: .flv\nSize: 23 MB\nResolution: 640 x 480\nDuration: 7:31 min\n\nHave Fun\n\nScreenshot:\n &lt;a href=&quot;\nhttp://www.yourfreeporn.tv/showimage.asp?im=/files/imghost/79435623/31468871.jpg&quot; rel=&quot;nofollow&quot; target=&quot;_NEW&quot;&gt;\nhttp://www.yourfreeporn.tv/showimage.asp?im=/files/imghost/79435623/31468871.jpg&lt;/a&gt;","torrent":{"xt":"urn:btih:e9f2dd2d0c2ff90c8db23a64252383c951dd2c65","amp;dn":"Let%27s+Do+Something+Exciting%2C+Baby.+Let%27s+Share+Our+Sexlife+Onlin","amp;tr":["udp%3A%2F%2Ftracker.openbittorrent.com%3A80","udp%3A%2F%2Fopen.demonii.com%3A1337","udp%3A%2F%2Ftracker.coppersurfer.tk%3A6969","udp%3A%2F%2Fexodus.desync.com%3A6969"],"infoHash":"e9f2dd2d0c2ff90c8db23a64252383c951dd2c65","infoHashBuffer":{"type":"Buffer","data":[233,242,221,45,12,47,249,12,141,178,58,100,37,35,131,201,81,221,44,101]},"announce":[],"urlList":[]}}