{"title":"In X Cess - Japanese Video Magazine 10","uid":9720929,"size":892973801,"categoryP":"porn","categoryS":"movies","magnet":"?xt=urn:btih:f6c4e4d1813e102589a984b5ec32063814a150ec&amp;dn=In+X+Cess+-+Japanese+Video+Magazine+10&amp;tr=udp%3A%2F%2Ftracker.openbittorrent.com%3A80&amp;tr=udp%3A%2F%2Fopen.demonii.com%3A1337&amp;tr=udp%3A%2F%2Ftracker.coppersurfer.tk%3A6969&amp;tr=udp%3A%2F%2Fexodus.desync.com%3A6969","seeders":0,"leechers":2,"uploader":"irealu69","files":-1,"time":1394235320,"description":"In X Cess - Japanese Video Magazine 10\n~~~~~~~~~~~~~~~~~~~~~~~~~~~~~~~~~~~~~~\n\nScreenshots:\n~~~~~~~~~~~~\n &lt;a href=&quot;\nhttp://picturescream.com/x/clean/fHNc&quot; rel=&quot;nofollow&quot; target=&quot;_NEW&quot;&gt;\nhttp://picturescream.com/x/clean/fHNc&lt;/a&gt;\n &lt;a href=&quot;\nhttp://picturescream.com/x/clean/fHNl&quot; rel=&quot;nofollow&quot; target=&quot;_NEW&quot;&gt;\nhttp://picturescream.com/x/clean/fHNl&lt;/a&gt;\n &lt;a href=&quot;\nhttp://picturescream.com/x/clean/fHNu&quot; rel=&quot;nofollow&quot; target=&quot;_NEW&quot;&gt;\nhttp://picturescream.com/x/clean/fHNu&lt;/a&gt;\n &lt;a href=&quot;\nhttp://picturescream.com/x/clean/fHNw&quot; rel=&quot;nofollow&quot; target=&quot;_NEW&quot;&gt;\nhttp://picturescream.com/x/clean/fHNw&lt;/a&gt;\n &lt;a href=&quot;\nhttp://picturescream.com/x/clean/fHfN&quot; rel=&quot;nofollow&quot; target=&quot;_NEW&quot;&gt;\nhttp://picturescream.com/x/clean/fHfN&lt;/a&gt;\n\n\nVideos Info:\n~~~~~~~~~~~~\nSize: 852 MB\nResolution: 512x384 ","torrent":{"xt":"urn:btih:f6c4e4d1813e102589a984b5ec32063814a150ec","amp;dn":"In+X+Cess+-+Japanese+Video+Magazine+10","amp;tr":["udp%3A%2F%2Ftracker.openbittorrent.com%3A80","udp%3A%2F%2Fopen.demonii.com%3A1337","udp%3A%2F%2Ftracker.coppersurfer.tk%3A6969","udp%3A%2F%2Fexodus.desync.com%3A6969"],"infoHash":"f6c4e4d1813e102589a984b5ec32063814a150ec","infoHashBuffer":{"type":"Buffer","data":[246,196,228,209,129,62,16,37,137,169,132,181,236,50,6,56,20,161,80,236]},"announce":[],"urlList":[]}}